nndesigner/__init__.py
nndesigner/__main__.py
nndesigner/main.py
nndesigner/config/system/node_groups.json
nndesigner/system_op/__init__.py
nndesigner/system_op/io.py
nndesigner/tools/codegen.py
nndesigner/tools/demo_codegen.py
nndesigner/tools/demo_codegen_results.py
nndesigner/utils/base.py
nndesigner/view/__init__.py
nndesigner/view/custom_node.py
nndesigner/view/custom_widget.py
nndesigner/view/graph_widget.py
nndesigner/view/node_panel.py
nndesigner/view/view.py
nndesigner-0.2.0.dist-info/METADATA
nndesigner-0.2.0.dist-info/WHEEL
nndesigner-0.2.0.dist-info/entry_points.txt
nndesigner-0.2.0.dist-info/licenses/LICENSE
nndesigner-0.2.0.dist-info/RECORD
