Metadata-Version: 2.4
Name: nndesigner
Version: 0.2.0
Summary: A visual deep learning model designer based on PyTorch.
Project-URL: Homepage, https://github.com/xiaoqiang-cheng/nndesigner
Author-email: xiaoqiang cheng <xiaoqiang.cheng@foxmail.com>
License:                     GNU GENERAL PUBLIC LICENSE
License-File: LICENSE
Classifier: License :: OSI Approved :: GNU General Public License (GPL)
Classifier: Operating System :: OS Independent
Classifier: Programming Language :: Python :: 3
Requires-Python: >=3.7
Requires-Dist: nodegraphqt>=0.5
Requires-Dist: numpy>=1.20
Requires-Dist: pyside6>=6.2
Provides-Extra: dev
Requires-Dist: black>=23.0; extra == 'dev'
Requires-Dist: flake8>=6.0; extra == 'dev'
Requires-Dist: pytest>=7.0; extra == 'dev'
Provides-Extra: torch
Requires-Dist: torch>=1.12; extra == 'torch'
